exif/__init__.py
exif/apps.py
exif/classes.py
exif/handlers.py
exif/links.py
exif/managers.py
exif/models.py
exif/settings.py
exif/urls.py
exif/views.py
exif/backends/__init__.py
exif/backends/exiftool.py
exif/backends/literals.py
exif/migrations/0001_initial.py
exif/migrations/__init__.py
exif/tests/__init__.py
exif/tests/literals.py
exif/tests/test_classes.py
exif/tests/test_models.py
exif/tests/test_views.py
mayan_exif-1.0.0.dist-info/DESCRIPTION.rst
mayan_exif-1.0.0.dist-info/METADATA
mayan_exif-1.0.0.dist-info/RECORD
mayan_exif-1.0.0.dist-info/WHEEL
mayan_exif-1.0.0.dist-info/metadata.json
mayan_exif-1.0.0.dist-info/top_level.txt
