Metadata-Version: 2.0
Name: mayan-exif
Version: 1.0.0
Summary: EXIF data extraction app for Mayan EDMS.
Home-page: https://gitlab.com/mayan-edms/exif
Author: Roberto Rosario
Author-email: roberto.rosario@mayan-edms.com
License: The MIT License (MIT)
Requires-Dist: sh (==1.11)
